LICENSE.txt
MANIFEST.in
README.md
requirements.txt
setup.py
test-requirements.txt
opsgenie_swagger/__init__.py
opsgenie_swagger/api_client.py
opsgenie_swagger/configuration.py
opsgenie_swagger/rest.py
opsgenie_swagger.egg-info/PKG-INFO
opsgenie_swagger.egg-info/SOURCES.txt
opsgenie_swagger.egg-info/dependency_links.txt
opsgenie_swagger.egg-info/requires.txt
opsgenie_swagger.egg-info/top_level.txt
opsgenie_swagger/api/__init__.py
opsgenie_swagger/api/account_api.py
opsgenie_swagger/api/alert_api.py
opsgenie_swagger/api/contact_api.py
opsgenie_swagger/api/custom_user_role_api.py
opsgenie_swagger/api/deprecated_policy_api.py
opsgenie_swagger/api/escalation_api.py
opsgenie_swagger/api/forwarding_rule_api.py
opsgenie_swagger/api/heartbeat_api.py
opsgenie_swagger/api/integration_action_api.py
opsgenie_swagger/api/integration_api.py
opsgenie_swagger/api/maintenance_api.py
opsgenie_swagger/api/notification_rule_api.py
opsgenie_swagger/api/notification_rule_step_api.py
opsgenie_swagger/api/policy_api.py
opsgenie_swagger/api/schedule_api.py
opsgenie_swagger/api/schedule_override_api.py
opsgenie_swagger/api/schedule_rotation_api.py
opsgenie_swagger/api/team_api.py
opsgenie_swagger/api/team_member_api.py
opsgenie_swagger/api/team_role_api.py
opsgenie_swagger/api/team_routing_rule_api.py
opsgenie_swagger/api/user_api.py
opsgenie_swagger/api/who_is_on_call_api.py
opsgenie_swagger/models/__init__.py
opsgenie_swagger/models/account_info.py
opsgenie_swagger/models/account_plan.py
opsgenie_swagger/models/ack_integration_action.py
opsgenie_swagger/models/acknowledge_alert_payload.py
opsgenie_swagger/models/action_categorized.py
opsgenie_swagger/models/action_mapping.py
opsgenie_swagger/models/add_details_to_alert_payload.py
opsgenie_swagger/models/add_note_integration_action.py
opsgenie_swagger/models/add_note_to_alert_payload.py
opsgenie_swagger/models/add_responder_to_alert_payload.py
opsgenie_swagger/models/add_tags_to_alert_payload.py
opsgenie_swagger/models/add_team_member_payload.py
opsgenie_swagger/models/add_team_to_alert_payload.py
opsgenie_swagger/models/airbrake_integration.py
opsgenie_swagger/models/alert.py
opsgenie_swagger/models/alert_action_payload.py
