Metadata-Version: 1.0
Name: opsgenie-swagger
Version: 1.0.7
Summary: OpsGenie REST API
Home-page: https://github.com/opsgenie/opsgenie-python-sdk
Author: UNKNOWN
Author-email: UNKNOWN
License: UNKNOWN
Keywords: Swagger,OpsGenie REST API
Platform: UNKNOWN
